affordable/__init__.py
affordable/affordable.py
affordable/game.py
samples/__init__.py
samples/demo.py
affordable-0.0.1.dist-info/LICENSE
affordable-0.0.1.dist-info/METADATA
affordable-0.0.1.dist-info/WHEEL
affordable-0.0.1.dist-info/top_level.txt
affordable-0.0.1.dist-info/RECORD
